{
	"configurations" : 
	[
		{
			"directories" : 
			[
				{
					"build" : ".",
					"jsonFile" : "directory-.-Debug-f5ebdc15457944623624.json",
					"minimumCMakeVersion" : 
					{
						"string" : "3.29"
					},
					"projectIndex" : 0,
					"source" : ".",
					"targetIndexes" : 
					[
						0
					]
				}
			],
			"name" : "Debug",
			"projects" : 
			[
				{
					"directoryIndexes" : 
					[
						0
					],
					"name" : "Radix_Sort_Negative_Numbers",
					"targetIndexes" : 
					[
						0
					]
				}
			],
			"targets" : 
			[
				{
					"directoryIndex" : 0,
					"id" : "Radix_Sort_Negative_Numbers::@6890427a1f51a3e7e1df",
					"jsonFile" : "target-Radix_Sort_Negative_Numbers-Debug-c1ecb8ecf019a3ec0c6a.json",
					"name" : "Radix_Sort_Negative_Numbers",
					"projectIndex" : 0
				}
			]
		}
	],
	"kind" : "codemodel",
	"paths" : 
	{
		"build" : "/Volumes/T7 Shield/IIT Folder/DSA Coding/Sorting-Searching/Radix-Sort-Negative_Numbers/cmake-build-debug",
		"source" : "/Volumes/T7 Shield/IIT Folder/DSA Coding/Sorting-Searching/Radix-Sort-Negative_Numbers"
	},
	"version" : 
	{
		"major" : 2,
		"minor" : 7
	}
}
